[
    {
        "name": "小米玩机交流总群",
        "limit": "QQ群-500人",
        "groupNumber": "676581092",
        "qrcode": "/images/qrcodes/qqqun-xmwjzq.webp",
        "joinLink": "https://qm.qq.com/q/rEYFmCSdIO",
        "analyticsEvent": "加入群聊1"
    },
    {
        "name": "小米玩机交流群-分群",
        "limit": "QQ群-500人",
        "groupNumber": "921998770",
        "qrcode": "/images/qrcodes/qqqun-xmwj2.webp",
        "joinLink": "https://qm.qq.com/q/Qy1TiDrhsq",
        "analyticsEvent": "加入群聊1"
    },
    {
        "name": "澎湃解锁工具箱(hout)交流总群",
        "limit": "QQ群-500人",
        "groupNumber": "921998770",
        "qrcode": "/images/qrcodes/qqqun-hout.webp",
        "joinLink": "https://qm.qq.com/q/1mdbZBhcEw",
        "analyticsEvent": "加入群聊1"
    },
    {
        "name": "QQ频道",
        "groupNumber": "4k233e56bg",
        "qrcode": "/images/qrcodes/qqpd.webp",
        "joinLink": "https://pd.qq.com/s/ausyns0uk?b=5",
        "analyticsEvent": "加入QQ频道"
    }
]